{
  "todos": [
    {
      "id": 1686231042076,
      "title": "rfd",
      "completed": true,
      "important": true
    },
    {
      "id": 1686231747044,
      "title": "dsfsf",
      "completed": false,
      "important": false
    },
    {
      "id": 1686232933580,
      "title": "fg",
      "completed": true,
      "important": true
    },
    {
      "id": 1686232934100,
      "title": "dgv",
      "completed": false,
      "important": false
    },
    {
      "id": 1686233644698,
      "title": " ",
      "completed": false,
      "important": true
    }
  ]
}